vardefunc/__init__.py
vardefunc/mask.py
vardefunc/misc.py
vardefunc/noise.py
vardefunc/ocr.py
vardefunc/py.typed
vardefunc/scale.py
vardefunc/types.py
vardefunc/util.py
vardefunc/vsjet_proxy.py
vardefunc-0.11.1.dist-info/METADATA
vardefunc-0.11.1.dist-info/WHEEL
vardefunc-0.11.1.dist-info/licenses/LICENSE
vardefunc-0.11.1.dist-info/RECORD
